{
  "id":"org.apache.httpcomponents/httpclient",
  "artifacts":[
    {
      "hash":"7a1791f3ef17acfb75d4c6a3e124b9a96946e02e2381e3f59f5bc500a7607208",
      "attributes":[
        {
          "configuration":[
            "default"
          ]
        }
      ],
      "filename":"httpclient-4.2.jar"
    },
    {
      "hash":"9ccaaa3754c1895c17abdc1b97259294ac885be0fdf3d06508162c94c527295d",
      "attributes":[
        {
          "configuration":[
            "sources"
          ]
        }
      ],
      "filename":"httpclient-4.2-sources.jar"
    }
  ],
  "attributes":[
    {
      "organization":[
        "org.apache.httpcomponents"
      ]
    },
    {
      "name":[
        "httpclient"
      ]
    },
    {
      "version":[
        "4.2"
      ]
    },
    {
      "configuration":[
        "compile",
        "runtime"
      ]
    }
  ],
  "dependencies":[
    {
      "id":"org.apache.httpcomponents/httpcore",
      "constraints":[
        {
          "organization":[
            "org.apache.httpcomponents"
          ]
        },
        {
          "name":[
            "httpcore"
          ]
        },
        {
          "version":[
            "4.2"
          ]
        }
      ]
    },
    {
      "id":"commons-logging/commons-logging",
      "constraints":[
        {
          "organization":[
            "commons-logging"
          ]
        },
        {
          "name":[
            "commons-logging"
          ]
        },
        {
          "version":[
            "1.1.1"
          ]
        }
      ]
    },
    {
      "id":"commons-codec/commons-codec",
      "constraints":[
        {
          "organization":[
            "commons-codec"
          ]
        },
        {
          "name":[
            "commons-codec"
          ]
        },
        {
          "version":[
            "1.6"
          ]
        }
      ]
    }
  ]
}